mphapi/__init__.py
mphapi/claim.py
mphapi/client.py
mphapi/client_test.py
mphapi/credentials.py
mphapi/date.py
mphapi/env.py
mphapi/fields.py
mphapi/pricing.py
mphapi/py.typed
mphapi/response.py
mphapi/snapshots/client_test/test_client/hcfa.json
mphapi/snapshots/client_test/test_client/inpatient.json
mphapi/snapshots/client_test/test_client/outpatient.json
mphapi/testdata/hcfa.json
mphapi/testdata/inpatient.json
mphapi/testdata/outpatient.json
mphapi-1.13.1.dist-info/METADATA
mphapi-1.13.1.dist-info/WHEEL
mphapi-1.13.1.dist-info/RECORD
