Metadata-Version: 2.4
Name: mphapi
Version: 1.13.1
Summary: A Python interface to the MyPriceHealth API
Author: David Archibald
Author-email: davidarchibald@myprice.health
Requires-Python: >=3.12,<4.0
Classifier: Programming Language :: Python :: 3
Classifier: Programming Language :: Python :: 3.12
Classifier: Programming Language :: Python :: 3.13
Classifier: Programming Language :: Python :: 3.14
Requires-Dist: pydantic (>=2.6.4,<3.0.0)
Requires-Dist: python-dotenv (>=1.1.1,<2.0.0)
Requires-Dist: requests (>=2.31.0,<3.0.0)
